mugideploy/__init__.py
mugideploy/__main__.py
mugideploy/cli.py
mugideploy/readme.py
mugideploy-0.0.30.dist-info/LICENSE
mugideploy-0.0.30.dist-info/METADATA
mugideploy-0.0.30.dist-info/WHEEL
mugideploy-0.0.30.dist-info/entry_points.txt
mugideploy-0.0.30.dist-info/top_level.txt
mugideploy-0.0.30.dist-info/RECORD
