Metadata-Version: 2.2
Name: mugideploy
Version: 0.0.30
Summary: C++ deploy utility
Home-page: https://github.com/mugiseyebrows/mugideploy
Author: Doronin Stanislav
Author-email: mugisbrows@gmail.com
Classifier: Programming Language :: Python :: 3
Classifier: License :: OSI Approved :: MIT License
Requires-Python: >=3.5
License-File: LICENSE
Requires-Dist: pefile
Requires-Dist: colorama
Requires-Dist: treelib
Dynamic: author
Dynamic: author-email
Dynamic: classifier
Dynamic: description
Dynamic: description-content-type
Dynamic: home-page
Dynamic: requires-dist
Dynamic: requires-python
Dynamic: summary
